MANIFEST.in
README.rst
setup.py
kikyo_api/__init__.py
kikyo_api/client.py
kikyo_api/errors.py
kikyo_api/serializer.py
kikyo_api/utils.py
kikyo_api.egg-info/PKG-INFO
kikyo_api.egg-info/SOURCES.txt
kikyo_api.egg-info/dependency_links.txt
kikyo_api.egg-info/not-zip-safe
kikyo_api.egg-info/requires.txt
kikyo_api.egg-info/top_level.txt
kikyo_api/nsclient/__init__.py
kikyo_api/nsclient/base.py
kikyo_api/nsclient/oss.py
kikyo_api/nsclient/search.py
requirements/docs.txt
tests/__init__.py