Metadata-Version: 1.2
Name: kikyo-api
Version: 0.8.4
Summary: kikyo API
Home-page: UNKNOWN
License: UNKNOWN
Platform: UNKNOWN
Requires-Python: >=3.6
